{
  "@context": {
    "bcnbio": "http://datos.bcn.cl/ontologies/bcn-biographies#",
    "foaf": "http://xmlns.com/foaf/0.1/",
    "rdf": "http://www.w3.org/1999/02/22-rdf-syntax-ns#",
    "rdfs": "http://www.w3.org/2000/01/rdf-schema#",
    "schema": "http://schema.org/",
    "xsd": "http://www.w3.org/2001/XMLSchema#"
  },
  "@graph": [
    {
      "@id": "http://datos.bcn.cl/recurso/persona/3494/cargoComision/16",
      "@type": "schema:OrganizationRole",
      "bcnbio:ParliamentaryPeriod": "2006-2010",
      "schema:Organization": "Cámara",
      "schema:additionalType": "Comisión Especial",
      "schema:endDate": {
        "@type": "xsd:date",
        "@value": "2010-03-10"
      },
      "schema:name": "Turismo",
      "schema:roleName": "miembro",
      "schema:startDate": {
        "@type": "xsd:date",
        "@value": "2006-03-11"
      }
    },
    {
      "@id": "http://datos.bcn.cl/recurso/persona/3494/cargoComision/17",
      "@type": "schema:OrganizationRole",
      "bcnbio:ParliamentaryPeriod": "2010-2018",
      "schema:Organization": "Senado",
      "schema:additionalType": "Comisión Permanente",
      "schema:endDate": {
        "@type": "xsd:date",
        "@value": "2018-03-10"
      },
      "schema:name": "Medio Ambiente y Bienes Nacionales",
      "schema:roleName": "miembro",
      "schema:startDate": {
        "@type": "xsd:date",
        "@value": "2010-03-11"
      },
      "schema:url": {
        "@id": "http://www.senado.cl/appsenado/index.php?mo=comisiones&ac=ficha&id=193&tipo_comision=10"
      }
    },
    {
      "@id": "http://datos.bcn.cl/recurso/persona/3494/cargoComision/14",
      "@type": "schema:OrganizationRole",
      "bcnbio:ParliamentaryPeriod": "2006-2010",
      "schema:Organization": "Cámara",
      "schema:additionalType": "Comisión Permanente",
      "schema:endDate": {
        "@type": "xsd:date",
        "@value": "2010-03-10"
      },
      "schema:name": "Relaciones Exteriores, Asuntos Interparlamentarios e Integración Latinoamericana",
      "schema:roleName": "miembro",
      "schema:startDate": {
        "@type": "xsd:date",
        "@value": "2006-03-11"
      },
      "schema:url": {
        "@id": "https://www.camara.cl/trabajamos/comision_portada.aspx?prmID=406"
      }
    },
    {
      "@id": "http://datos.bcn.cl/recurso/persona/3494",
      "@type": [
        "schema:Person",
        "foaf:Person"
      ],
      "bcnbio:PoliticalParty": "Partido Socialista de Chile",
      "bcnbio:surnameOfFather": "Allende",
      "bcnbio:surnameOfMather": "Bussi",
      "foaf:depiction": {
        "@id": "http://biografias.bcn.cl/images/d/df/Mar%C3%ADa_Isabel_Allende_Bussi.jpg"
      },
      "foaf:givenName": "María Isabel",
      "foaf:name": "María Isabel Allende Bussi",
      "schema:OrganizationRole": [
        {
          "@id": "http://datos.bcn.cl/recurso/persona/3494/cargoComision/13"
        },
        {
          "@id": "http://datos.bcn.cl/recurso/persona/3494/cargoComision/16"
        },
        {
          "@id": "http://datos.bcn.cl/recurso/persona/3494/cargoComision/11"
        },
        {
          "@id": "http://datos.bcn.cl/recurso/persona/3494/cargo/2"
        },
        {
          "@id": "http://datos.bcn.cl/recurso/persona/3494/cargoComision/15"
        },
        {
          "@id": "http://datos.bcn.cl/recurso/persona/3494/cargoComision/26"
        },
        {
          "@id": "http://datos.bcn.cl/recurso/persona/3494/cargoComision/17"
        },
        {
          "@id": "http://datos.bcn.cl/recurso/persona/3494/cargoComision/5"
        },
        {
          "@id": "http://datos.bcn.cl/recurso/persona/3494/cargoComision/6"
        },
        {
          "@id": "http://datos.bcn.cl/recurso/persona/3494/cargoComision/19"
        },
        {
          "@id": "http://datos.bcn.cl/recurso/persona/3494/cargoComision/12"
        },
        {
          "@id": "http://datos.bcn.cl/recurso/persona/3494/cargoComision/1"
        },
        {
          "@id": "http://datos.bcn.cl/recurso/persona/3494/cargoComision/24"
        },
        {
          "@id": "http://datos.bcn.cl/recurso/persona/3494/cargo/1"
        },
        {
          "@id": "http://datos.bcn.cl/recurso/persona/3494/cargoComision/7"
        },
        {
          "@id": "http://datos.bcn.cl/recurso/persona/3494/cargoComision/22"
        },
        {
          "@id": "http://datos.bcn.cl/recurso/persona/3494/cargoComision/25"
        },
        {
          "@id": "http://datos.bcn.cl/recurso/persona/3494/cargo/4"
        },
        {
          "@id": "http://datos.bcn.cl/recurso/persona/3494/cargo/6"
        },
        {
          "@id": "http://datos.bcn.cl/recurso/persona/3494/cargoComision/2"
        },
        {
          "@id": "http://datos.bcn.cl/recurso/persona/3494/cargoComision/23"
        },
        {
          "@id": "http://datos.bcn.cl/recurso/persona/3494/cargoComision/21"
        },
        {
          "@id": "http://datos.bcn.cl/recurso/persona/3494/cargoComision/10"
        },
        {
          "@id": "http://datos.bcn.cl/recurso/persona/3494/cargoComision/4"
        },
        {
          "@id": "http://datos.bcn.cl/recurso/persona/3494/cargo/5"
        },
        {
          "@id": "http://datos.bcn.cl/recurso/persona/3494/cargoComision/14"
        },
        {
          "@id": "http://datos.bcn.cl/recurso/persona/3494/cargoComision/27"
        },
        {
          "@id": "http://datos.bcn.cl/recurso/persona/3494/cargoComision/8"
        },
        {
          "@id": "http://datos.bcn.cl/recurso/persona/3494/cargoComision/9"
        },
        {
          "@id": "http://datos.bcn.cl/recurso/persona/3494/cargoComision/20"
        },
        {
          "@id": "http://datos.bcn.cl/recurso/persona/3494/cargo/3"
        },
        {
          "@id": "http://datos.bcn.cl/recurso/persona/3494/cargoComision/3"
        },
        {
          "@id": "http://datos.bcn.cl/recurso/persona/3494/cargoComision/18"
        }
      ],
      "schema:birthDate": {
        "@type": "xsd:date",
        "@value": "1945-01-18"
      },
      "schema:birthPlace": "Santiago, Chile",
      "schema:children": [
        "Gonzalo",
        "Marcia"
      ],
      "schema:gender": "femenino",
      "schema:hasOccupation": "Socióloga; Máster en Sociología y Ciencia Política",
      "schema:parent": [
        "Mercedes Hortensia, Bussi Soto",
        "Salvador Guillermo, Allende Gossens"
      ]
    },
    {
      "@id": "http://datos.bcn.cl/recurso/persona/3494/cargoComision/12",
      "@type": "schema:OrganizationRole",
      "bcnbio:ParliamentaryPeriod": "2006-2010",
      "schema:Organization": "Cámara",
      "schema:additionalType": "Comisión Permanente",
      "schema:endDate": {
        "@type": "xsd:date",
        "@value": "2010-03-10"
      },
      "schema:name": "Cultura y de las Artes",
      "schema:roleName": "miembro",
      "schema:startDate": {
        "@type": "xsd:date",
        "@value": "2006-03-11"
      },
      "schema:url": {
        "@id": "https://www.camara.cl/trabajamos/comision_portada.aspx?prmID=496"
      }
    },
    {
      "@id": "http://datos.bcn.cl/recurso/persona/3494/cargoComision/13",
      "@type": "schema:OrganizationRole",
      "bcnbio:ParliamentaryPeriod": "2006-2010",
      "schema:Organization": "Cámara",
      "schema:additionalType": "Comisión Permanente",
      "schema:endDate": {
        "@type": "xsd:date",
        "@value": "2010-03-10"
      },
      "schema:name": "Minería y Energía",
      "schema:roleName": "miembro",
      "schema:startDate": {
        "@type": "xsd:date",
        "@value": "2006-03-11"
      },
      "schema:url": {
        "@id": "https://www.camara.cl/trabajamos/comision_portada.aspx?prmID=409"
      }
    },
    {
      "@id": "http://datos.bcn.cl/recurso/persona/3494/cargoComision/10",
      "@type": "schema:OrganizationRole",
      "bcnbio:ParliamentaryPeriod": "2002-2006",
      "schema:Organization": "Cámara",
      "schema:additionalType": "Comisión Permanente",
      "schema:endDate": {
        "@type": "xsd:date",
        "@value": "2006-03-10"
      },
      "schema:name": "Relaciones Exteriores, Asuntos Interparlamentarios e Integración Latinoamericana",
      "schema:roleName": "miembro",
      "schema:startDate": {
        "@type": "xsd:date",
        "@value": "2002-03-11"
      },
      "schema:url": {
        "@id": "https://www.camara.cl/trabajamos/comision_portada.aspx?prmID=406"
      }
    },
    {
      "@id": "http://datos.bcn.cl/recurso/persona/3494/cargoComision/11",
      "@type": "schema:OrganizationRole",
      "bcnbio:ParliamentaryPeriod": "2002-2006",
      "schema:Organization": "Cámara",
      "schema:additionalType": "Comisión Permanente",
      "schema:endDate": {
        "@type": "xsd:date",
        "@value": "2006-03-10"
      },
      "schema:name": "Familia",
      "schema:roleName": "miembro",
      "schema:startDate": {
        "@type": "xsd:date",
        "@value": "2002-03-11"
      },
      "schema:url": {
        "@id": "https://www.camara.cl/trabajamos/comision_portada.aspx?prmID=415"
      }
    },
    {
      "@id": "http://datos.bcn.cl/recurso/persona/3494/cargoComision/18",
      "@type": "schema:OrganizationRole",
      "bcnbio:ParliamentaryPeriod": "2010-2018",
      "schema:Organization": "Senado",
      "schema:additionalType": "Comisión Permanente",
      "schema:endDate": {
        "@type": "xsd:date",
        "@value": "2018-03-10"
      },
      "schema:name": "Minería y Energía",
      "schema:roleName": "miembro",
      "schema:startDate": {
        "@type": "xsd:date",
        "@value": "2010-03-11"
      },
      "schema:url": {
        "@id": "http://www.senado.cl/appsenado/index.php?mo=comisiones&ac=ficha&id=196&tipo_comision=10"
      }
    },
    {
      "@id": "http://datos.bcn.cl/recurso/persona/3494/cargoComision/19",
      "@type": "schema:OrganizationRole",
      "bcnbio:ParliamentaryPeriod": "2010-2018",
      "schema:Organization": "Senado",
      "schema:additionalType": "Comisión Permanente",
      "schema:endDate": {
        "@type": "xsd:date",
        "@value": "2018-03-10"
      },
      "schema:name": "Ética y Transparencia",
      "schema:roleName": "miembro",
      "schema:startDate": {
        "@type": "xsd:date",
        "@value": "2010-03-11"
      },
      "schema:url": {
        "@id": "http://www.senado.cl/appsenado/index.php?mo=comisiones&ac=ficha&id=718&tipo_comision=10"
      }
    },
    {
      "@id": "http://datos.bcn.cl/recurso/persona/3494/cargoComision/4",
      "@type": "schema:OrganizationRole",
      "bcnbio:ParliamentaryPeriod": "1994-1998",
      "schema:Organization": "Cámara",
      "schema:additionalType": "Comisión Permanente",
      "schema:endDate": {
        "@type": "xsd:date",
        "@value": "1998-03-10"
      },
      "schema:name": "Relaciones Exteriores, Asuntos Interparlamentarios e Integración Latinoamericana",
      "schema:roleName": "miembro",
      "schema:startDate": {
        "@type": "xsd:date",
        "@value": "1994-03-11"
      },
      "schema:url": {
        "@id": "https://www.camara.cl/trabajamos/comision_portada.aspx?prmID=406"
      }
    },
    {
      "@id": "http://datos.bcn.cl/recurso/persona/3494/cargoComision/5",
      "@type": "schema:OrganizationRole",
      "bcnbio:ParliamentaryPeriod": "1994-1998",
      "schema:Organization": "Cámara",
      "schema:additionalType": "Comisión Permanente",
      "schema:endDate": {
        "@type": "xsd:date",
        "@value": "1998-03-10"
      },
      "schema:name": "Gobierno Interior, Regionalización, Planificación y Desarrollo Social",
      "schema:roleName": "miembro",
      "schema:startDate": {
        "@type": "xsd:date",
        "@value": "1994-03-11"
      },
      "schema:url": {
        "@id": "https://www.camara.cl/trabajamos/comision_portada.aspx?prmID=414"
      }
    },
    {
      "@id": "http://datos.bcn.cl/recurso/persona/3494/cargoComision/6",
      "@type": "schema:OrganizationRole",
      "bcnbio:ParliamentaryPeriod": "1998-2002",
      "schema:Organization": "Cámara",
      "schema:additionalType": "Comisión Especial",
      "schema:endDate": {
        "@type": "xsd:date",
        "@value": "2002-03-10"
      },
      "schema:name": "Drogas",
      "schema:roleName": "miembro",
      "schema:startDate": {
        "@type": "xsd:date",
        "@value": "1998-03-11"
      }
    },
    {
      "@id": "http://datos.bcn.cl/recurso/persona/3494/cargoComision/7",
      "@type": "schema:OrganizationRole",
      "bcnbio:ParliamentaryPeriod": "1998-2002",
      "schema:Organization": "Cámara",
      "schema:additionalType": "Comisión Permanente",
      "schema:endDate": {
        "@type": "xsd:date",
        "@value": "2002-03-10"
      },
      "schema:name": "Familia",
      "schema:roleName": "presidente",
      "schema:startDate": {
        "@type": "xsd:date",
        "@value": "1998-03-11"
      },
      "schema:url": {
        "@id": "https://www.camara.cl/trabajamos/comision_portada.aspx?prmID=415"
      }
    },
    {
      "@id": "http://datos.bcn.cl/recurso/persona/3494/cargoComision/1",
      "@type": "schema:OrganizationRole",
      "bcnbio:ParliamentaryPeriod": "1994-1998",
      "schema:Organization": "Cámara",
      "schema:additionalType": "Comisión Permanente",
      "schema:endDate": {
        "@type": "xsd:date",
        "@value": "1998-03-10"
      },
      "schema:name": "Familia",
      "schema:roleName": "miembro",
      "schema:startDate": {
        "@type": "xsd:date",
        "@value": "1994-03-11"
      },
      "schema:url": {
        "@id": "https://www.camara.cl/trabajamos/comision_portada.aspx?prmID=415"
      }
    },
    {
      "@id": "http://datos.bcn.cl/recurso/persona/3494/cargoComision/2",
      "@type": "schema:OrganizationRole",
      "bcnbio:ParliamentaryPeriod": "1994-1998",
      "schema:Organization": "Cámara",
      "schema:additionalType": "Comisión Permanente",
      "schema:endDate": {
        "@type": "xsd:date",
        "@value": "1998-03-10"
      },
      "schema:name": "Recursos Naturales, Bienes Nacionales y Medio Ambiente",
      "schema:roleName": "miembro",
      "schema:startDate": {
        "@type": "xsd:date",
        "@value": "1994-03-11"
      },
      "schema:url": {
        "@id": "https://www.camara.cl/trabajamos/comision_portada.aspx?prmID=405"
      }
    },
    {
      "@id": "http://datos.bcn.cl/recurso/persona/3494/cargoComision/3",
      "@type": "schema:OrganizationRole",
      "bcnbio:ParliamentaryPeriod": "1994-1998",
      "schema:Organization": "Cámara",
      "schema:additionalType": "Comisión Permanente",
      "schema:endDate": {
        "@type": "xsd:date",
        "@value": "1998-03-10"
      },
      "schema:name": "Ciencias y Tecnología",
      "schema:roleName": "miembro",
      "schema:startDate": {
        "@type": "xsd:date",
        "@value": "1994-03-11"
      },
      "schema:url": {
        "@id": "https://www.camara.cl/trabajamos/comision_portada.aspx?prmID=403"
      }
    },
    {
      "@id": "http://datos.bcn.cl/recurso/persona/3494/cargoComision/8",
      "@type": "schema:OrganizationRole",
      "bcnbio:ParliamentaryPeriod": "1998-2002",
      "schema:Organization": "Cámara",
      "schema:additionalType": "Comisión Permanente",
      "schema:endDate": {
        "@type": "xsd:date",
        "@value": "2002-03-10"
      },
      "schema:name": "Vivienda y Desarrollo Urbano",
      "schema:roleName": "miembro",
      "schema:startDate": {
        "@type": "xsd:date",
        "@value": "1998-03-11"
      },
      "schema:url": {
        "@id": "https://www.camara.cl/trabajamos/comision_portada.aspx?prmID=416"
      }
    },
    {
      "@id": "http://datos.bcn.cl/recurso/persona/3494/cargoComision/9",
      "@type": "schema:OrganizationRole",
      "bcnbio:ParliamentaryPeriod": "2002-2006",
      "schema:Organization": "Cámara",
      "schema:additionalType": "Comisión Especial",
      "schema:endDate": {
        "@type": "xsd:date",
        "@value": "2006-03-10"
      },
      "schema:name": "Beneficios para los Discapacitados",
      "schema:roleName": "miembro",
      "schema:startDate": {
        "@type": "xsd:date",
        "@value": "2002-03-11"
      }
    },
    {
      "@id": "http://datos.bcn.cl/recurso/persona/3494/cargoComision/27",
      "@type": "schema:OrganizationRole",
      "bcnbio:ParliamentaryPeriod": "2018-2026",
      "schema:Organization": "Senado",
      "schema:additionalType": "Comisión Especial",
      "schema:endDate": {
        "@type": "xsd:date",
        "@value": "2026-03-10"
      },
      "schema:name": "Especial encargada de tramitar proyectos de ley relacionados con los niños, niñas y adolescentes",
      "schema:roleName": "miembro",
      "schema:startDate": {
        "@type": "xsd:date",
        "@value": "2018-09-12"
      },
      "schema:url": {
        "@id": "http://www.senado.cl/appsenado/index.php?mo=comisiones&ac=ficha&id=1062&tipo_comision=10"
      }
    },
    {
      "@id": "http://datos.bcn.cl/recurso/persona/3494/cargoComision/26",
      "@type": "schema:OrganizationRole",
      "bcnbio:ParliamentaryPeriod": "2018-2026",
      "schema:Organization": "Senado",
      "schema:additionalType": "Comisión Especial",
      "schema:endDate": {
        "@type": "xsd:date",
        "@value": "2026-03-10"
      },
      "schema:name": "Especial Encargada de conocer iniciativas y tramitar proyectos de ley relacionados con la mujer y la igualdad de género",
      "schema:roleName": "miembro",
      "schema:startDate": {
        "@type": "xsd:date",
        "@value": "2018-09-12"
      },
      "schema:url": {
        "@id": "http://www.senado.cl/appsenado/index.php?mo=comisiones&ac=ficha&id=1126&tipo_comision=10"
      }
    },
    {
      "@id": "http://datos.bcn.cl/recurso/persona/3494/cargoComision/25",
      "@type": "schema:OrganizationRole",
      "bcnbio:ParliamentaryPeriod": "2018-2026",
      "schema:Organization": "Senado",
      "schema:additionalType": "Comisión Permanente",
      "schema:endDate": {
        "@type": "xsd:date",
        "@value": "2026-03-10"
      },
      "schema:name": "Minería y Energía",
      "schema:roleName": "miembro",
      "schema:startDate": {
        "@type": "xsd:date",
        "@value": "2018-03-11"
      },
      "schema:url": {
        "@id": "http://www.senado.cl/appsenado/index.php?mo=comisiones&ac=ficha&id=196&tipo_comision=10"
      }
    },
    {
      "@id": "http://datos.bcn.cl/recurso/persona/3494/cargoComision/24",
      "@type": "schema:OrganizationRole",
      "bcnbio:ParliamentaryPeriod": "2018-2026",
      "schema:Organization": "Senado",
      "schema:additionalType": "Comisión Especial",
      "schema:endDate": {
        "@type": "xsd:date",
        "@value": "2026-03-10"
      },
      "schema:name": "Recursos Hídricos, Desertificación y Sequía",
      "schema:roleName": "miembro",
      "schema:startDate": {
        "@type": "xsd:date",
        "@value": "2018-03-11"
      },
      "schema:url": {
        "@id": "http://www.senado.cl/appsenado/index.php?mo=comisiones&ac=ficha&id=1009&tipo_comision=10"
      }
    },
    {
      "@id": "http://datos.bcn.cl/recurso/persona/3494/cargoComision/23",
      "@type": "schema:OrganizationRole",
      "bcnbio:ParliamentaryPeriod": "2018-2026",
      "schema:Organization": "Senado",
      "schema:additionalType": "Comisión Permanente",
      "schema:endDate": {
        "@type": "xsd:date",
        "@value": "2026-03-10"
      },
      "schema:name": "Medio Ambiente y Bienes Nacionales",
      "schema:roleName": "presidente",
      "schema:startDate": {
        "@type": "xsd:date",
        "@value": "2018-03-11"
      },
      "schema:url": {
        "@id": "http://www.senado.cl/appsenado/index.php?mo=comisiones&ac=ficha&id=193&tipo_comision=10"
      }
    },
    {
      "@id": "http://datos.bcn.cl/recurso/persona/3494/cargoComision/22",
      "@type": "schema:OrganizationRole",
      "bcnbio:ParliamentaryPeriod": "2018-2026",
      "schema:Organization": "Senado",
      "schema:additionalType": "Comisión Especial",
      "schema:endDate": {
        "@type": "xsd:date",
        "@value": "2026-03-10"
      },
      "schema:name": "Zonas Extremas y Territorios Especiales",
      "schema:roleName": "miembro",
      "schema:startDate": {
        "@type": "xsd:date",
        "@value": "2018-03-11"
      },
      "schema:url": {
        "@id": "http://www.senado.cl/appsenado/index.php?mo=comisiones&ac=ficha&id=899&tipo_comision=10"
      }
    },
    {
      "@id": "http://datos.bcn.cl/recurso/persona/3494/cargoComision/21",
      "@type": "schema:OrganizationRole",
      "bcnbio:ParliamentaryPeriod": "2010-2018",
      "schema:Organization": "Senado",
      "schema:additionalType": "Comisión Especial",
      "schema:endDate": {
        "@type": "xsd:date",
        "@value": "2018-03-10"
      },
      "schema:name": "Recursos Hídricos, Desertificación y Sequía",
      "schema:roleName": "miembro",
      "schema:startDate": {
        "@type": "xsd:date",
        "@value": "2010-03-11"
      },
      "schema:url": {
        "@id": "http://www.senado.cl/appsenado/index.php?mo=comisiones&ac=ficha&id=1009&tipo_comision=10"
      }
    },
    {
      "@id": "http://datos.bcn.cl/recurso/persona/3494/cargoComision/20",
      "@type": "schema:OrganizationRole",
      "bcnbio:ParliamentaryPeriod": "2010-2018",
      "schema:Organization": "Senado",
      "schema:additionalType": "Comisión Permanente",
      "schema:endDate": {
        "@type": "xsd:date",
        "@value": "2018-03-10"
      },
      "schema:name": "Régimen Interior",
      "schema:roleName": "presidente",
      "schema:startDate": {
        "@type": "xsd:date",
        "@value": "2010-03-11"
      },
      "schema:url": {
        "@id": "http://www.senado.cl/appsenado/index.php?mo=comisiones&ac=ficha&id=201&tipo_comision=10"
      }
    },
    {
      "@id": "http://datos.bcn.cl/recurso/persona/3494/cargoComision/15",
      "@type": "schema:OrganizationRole",
      "bcnbio:ParliamentaryPeriod": "2006-2010",
      "schema:Organization": "Cámara",
      "schema:additionalType": "Comisión Especial",
      "schema:endDate": {
        "@type": "xsd:date",
        "@value": "2010-03-10"
      },
      "schema:name": "Beneficios para los Discapacitados",
      "schema:roleName": "miembro",
      "schema:startDate": {
        "@type": "xsd:date",
        "@value": "2006-03-11"
      }
    },
    {
      "@id": "http://datos.bcn.cl/recurso/persona/3494/cargo/6",
      "@type": "schema:OrganizationRole",
      "bcnbio:ParliamentaryPeriod": "2018-2026",
      "bcnbio:ofNamedPoliticalParty": "Partido Socialista de Chile",
      "bcnbio:representing": "6ta Circunscripción de Valparaíso",
      "schema:Organization": "Senado",
      "schema:endDate": {
        "@type": "xsd:date",
        "@value": "2026-03-10"
      },
      "schema:roleName": "Senadora",
      "schema:startDate": {
        "@type": "xsd:date",
        "@value": "2018-03-11"
      }
    },
    {
      "@id": "http://datos.bcn.cl/recurso/persona/3494/cargo/5",
      "@type": "schema:OrganizationRole",
      "bcnbio:ParliamentaryPeriod": "2010-2018",
      "bcnbio:ofNamedPoliticalParty": "Partido Socialista de Chile",
      "bcnbio:representing": "3a Circunscripción de Atacama",
      "schema:Organization": "Senado",
      "schema:endDate": {
        "@type": "xsd:date",
        "@value": "2018-03-10"
      },
      "schema:roleName": "Senadora",
      "schema:startDate": {
        "@type": "xsd:date",
        "@value": "2010-03-11"
      }
    },
    {
      "@id": "http://datos.bcn.cl/recurso/persona/3494/cargo/4",
      "@type": "schema:OrganizationRole",
      "bcnbio:ParliamentaryPeriod": "2006-2010",
      "bcnbio:ofNamedPoliticalParty": "Partido Socialista de Chile",
      "bcnbio:representing": "Distrito Nº 29 de Región Metropolitana",
      "schema:Organization": "Cámara",
      "schema:endDate": {
        "@type": "xsd:date",
        "@value": "2010-03-10"
      },
      "schema:roleName": "Diputada",
      "schema:startDate": {
        "@type": "xsd:date",
        "@value": "2006-03-11"
      }
    },
    {
      "@id": "http://datos.bcn.cl/recurso/persona/3494/cargo/3",
      "@type": "schema:OrganizationRole",
      "bcnbio:ParliamentaryPeriod": "2002-2006",
      "bcnbio:ofNamedPoliticalParty": "Partido Socialista de Chile",
      "bcnbio:representing": "Distrito Nº 29 de Región Metropolitana",
      "schema:Organization": "Cámara",
      "schema:endDate": {
        "@type": "xsd:date",
        "@value": "2006-03-10"
      },
      "schema:roleName": "Diputada",
      "schema:startDate": {
        "@type": "xsd:date",
        "@value": "2002-03-11"
      }
    },
    {
      "@id": "http://datos.bcn.cl/recurso/persona/3494/cargo/2",
      "@type": "schema:OrganizationRole",
      "bcnbio:ParliamentaryPeriod": "1998-2002",
      "bcnbio:ofNamedPoliticalParty": "Partido Socialista de Chile",
      "bcnbio:representing": "Distrito Nº 29 de Región Metropolitana",
      "schema:Organization": "Cámara",
      "schema:endDate": {
        "@type": "xsd:date",
        "@value": "2002-03-10"
      },
      "schema:roleName": "Diputada",
      "schema:startDate": {
        "@type": "xsd:date",
        "@value": "1998-03-11"
      }
    },
    {
      "@id": "http://datos.bcn.cl/recurso/persona/3494/cargo/1",
      "@type": "schema:OrganizationRole",
      "bcnbio:ParliamentaryPeriod": "1994-1998",
      "bcnbio:ofNamedPoliticalParty": "Partido Socialista de Chile",
      "bcnbio:representing": "Distrito Nº 9 de Región de Coquimbo",
      "schema:Organization": "Cámara",
      "schema:endDate": {
        "@type": "xsd:date",
        "@value": "1998-03-10"
      },
      "schema:roleName": "Diputada",
      "schema:startDate": {
        "@type": "xsd:date",
        "@value": "1994-03-11"
      }
    }
  ]
}